[
  {
    "ApiId": "/providers/microsoft.powerapps/apis/shared_sharepointonline",
    "CdpRevision": {
      "BaseUrl": "/",
      "LastChangedTimeString": "2024-04-23T17:02:01.9370000Z",
      "RevisionNumber": 1
    },
    "ConnectedDataSourceInfoNameMapping": {
      "{Attachments}": "Attachments",
      "{Attachments}@odata.type": "{Attachments} ({Attachments}@odata.type)",
      "{FilenameWithExtension}": "File name with extension",
      "{FullPath}": "Full Path",
      "{HasAttachments}": "Has attachments",
      "{Identifier}": "Identifier",
      "{IsFolder}": "IsFolder",
      "{Link}": "Link to item",
      "{ModerationComment}": "Comments associated with the content approval of this list item",
      "{ModerationStatus}": "Content approval status",
      "{Name}": "Name",
      "{Path}": "Folder path",
      "{Thumbnail}": "Thumbnail",
      "{TriggerWindowEndToken}": "Trigger Window End Token",
      "{TriggerWindowStartToken}": "Trigger Window Start Token",
      "{VersionNumber}": "Version number",
      "Author": "Created By",
      "Author#Claims": "Created By Claims",
      "Budget": "Budget",
      "City": "Destination: City",
      "ComplianceAssetId": "Compliance Asset Id",
      "CountryOrRegion": "Destination: Country/Region",
      "Created": "Created",
      "DispName": "Destination: Name",
      "Duration": "Date_Start",
      "Duration0": "Duration (Duration0)",
      "Editor": "Modified By",
      "Editor#Claims": "Modified By Claims",
      "ID": "ID",
      "Modified": "Modified",
      "OData__ColorTag": "Color Tag",
      "Participant": "Participant",
      "PostalCode": "Destination: Postal Code",
      "State": "Destination: State",
      "Street": "Destination: Street",
      "SydneyTrip2024": "Sydney Trip 2024",
      "Title": "Title",
      "TripName": "Trip :"
    },
    "DatasetName": "https://unisydneyedu.sharepoint.com/sites/TravelApp",
    "EncodeDataset": true,
    "IsSampleData": false,
    "IsWritable": true,
    "Name": "TravelApp",
    "Type": "ConnectedDataSourceInfo"
  }
]